{
  "project_info": {
    "project_number": "611321729894",
    "project_id": "alabenaissia-flutter-project0",
    "storage_bucket": "alabenaissia-flutter-project0.appspot.com"
  },
  "client": [
    {
      "client_info": {
        "mobilesdk_app_id": "1:611321729894:android:beb1fc3e9241a89ccaaea7",
        "android_client_info": {
          "package_name": "com.project0.project0"
        }
      },
      "oauth_client": [
        {
          "client_id": "611321729894-r3ilnhgaleejotpk04s3up6er4ucs0q8.apps.googleusercontent.com",
          "client_type": 3
        }
      ],
      "api_key": [
        {
          "current_key": "AIzaSyDM-KCl1Aq_pkmg5IqM_GaAkiEUaGayawA"
        }
      ],
      "services": {
        "appinvite_service": {
          "other_platform_oauth_client": [
            {
              "client_id": "611321729894-r3ilnhgaleejotpk04s3up6er4ucs0q8.apps.googleusercontent.com",
              "client_type": 3
            }
          ]
        }
      }
    }
  ],
  "configuration_version": "1"
}